[{
        "name": "angular-number-input",
        "html_url": "https://github.com/sagiegurari/angular-number-input",
        "description": "AngularJS number input directive.",
        "fork": false,
        "stargazers_count": 4,
        "language": "JavaScript",
        "forks_count": 0
    },
    {
        "name": "angular-web-notification",
        "html_url": "https://github.com/sagiegurari/angular-web-notification",
        "description": "Web Notifications AngularJS Service",
        "fork": false,
        "stargazers_count": 156,
        "language": "JavaScript",
        "forks_count": 27
    },
    {
        "name": "brackets-portable",
        "html_url": "https://github.com/sagiegurari/brackets-portable",
        "description": "Windows portable version of adobe brackets web development editor.",
        "fork": false,
        "stargazers_count": 98,
        "language": "HTML",
        "forks_count": 12
    },
    {
        "name": "cargo-make",
        "html_url": "https://github.com/sagiegurari/cargo-make",
        "description": "Rust task runner and build tool.",
        "fork": false,
        "stargazers_count": 115,
        "language": "Rust",
        "forks_count": 5
    },
    {
        "name": "ci_info",
        "html_url": "https://github.com/sagiegurari/ci_info",
        "description": "Provides current CI environment information.",
        "fork": false,
        "stargazers_count": 1,
        "language": "Rust",
        "forks_count": 0
    },
    {
        "name": "docker-cargo-make",
        "html_url": "https://github.com/sagiegurari/docker-cargo-make",
        "description": "Docker image with Rust and cargo-make preinstalled.",
        "fork": false,
        "stargazers_count": 1,
        "language": null,
        "forks_count": 0
    },
    {
        "name": "event-emitter-enhancer",
        "html_url": "https://github.com/sagiegurari/event-emitter-enhancer",
        "description": "Extends the Node.js events.EventEmitter to provide additional functionality.",
        "fork": false,
        "stargazers_count": 6,
        "language": "JavaScript",
        "forks_count": 0
    },
    {
        "name": "fax4j",
        "html_url": "https://github.com/sagiegurari/fax4j",
        "description": "Java fax library.",
        "fork": false,
        "stargazers_count": 9,
        "language": "Java",
        "forks_count": 5
    },
    {
        "name": "funcs-js",
        "html_url": "https://github.com/sagiegurari/funcs-js",
        "description": "Function wrappers for enhanced behavior.",
        "fork": false,
        "stargazers_count": 1,
        "language": "JavaScript",
        "forks_count": 0
    },
    {
        "name": "grunt-markdownlint",
        "html_url": "https://github.com/sagiegurari/grunt-markdownlint",
        "description": "A grunt task for markdown style checker and lint tool.",
        "fork": false,
        "stargazers_count": 3,
        "language": "JavaScript",
        "forks_count": 1
    },
    {
        "name": "js-project-commons",
        "html_url": "https://github.com/sagiegurari/js-project-commons",
        "description": "Common web and node.js grunt tasks/lint configs/md templates and so on...",
        "fork": false,
        "stargazers_count": 1,
        "language": "JavaScript",
        "forks_count": 0
    },
    {
        "name": "misc-test",
        "html_url": "https://github.com/sagiegurari/misc-test",
        "description": "misc tests",
        "fork": false,
        "stargazers_count": 1,
        "language": null,
        "forks_count": 0
    },
    {
        "name": "multiple-redis",
        "html_url": "https://github.com/sagiegurari/multiple-redis",
        "description": "Run redis commands against multiple redis instances.",
        "fork": false,
        "stargazers_count": 10,
        "language": "JavaScript",
        "forks_count": 1
    },
    {
        "name": "node-go-require",
        "html_url": "https://github.com/sagiegurari/node-go-require",
        "description": "Load Google GO files as any javascript modules under nodeJS runtime.",
        "fork": false,
        "stargazers_count": 52,
        "language": "JavaScript",
        "forks_count": 6
    },
    {
        "name": "node-later",
        "html_url": "https://github.com/sagiegurari/node-later",
        "description": "Defer function calls to the start of the next cycle.",
        "fork": false,
        "stargazers_count": 1,
        "language": "JavaScript",
        "forks_count": 0
    },
    {
        "name": "node-spider-script",
        "html_url": "https://github.com/sagiegurari/node-spider-script",
        "description": "Run spider script files as javascript modules in NodeJS.",
        "fork": false,
        "stargazers_count": 6,
        "language": "JavaScript",
        "forks_count": 0
    },
    {
        "name": "oracledb-upsert",
        "html_url": "https://github.com/sagiegurari/oracledb-upsert",
        "description": "UPSERT (insert/update) extension to oracledb",
        "fork": false,
        "stargazers_count": 2,
        "language": "JavaScript",
        "forks_count": 0
    },
    {
        "name": "run_script",
        "html_url": "https://github.com/sagiegurari/run_script",
        "description": "Run shell scripts in rust.",
        "fork": false,
        "stargazers_count": 3,
        "language": "Rust",
        "forks_count": 0
    },
    {
        "name": "rust_info",
        "html_url": "https://github.com/sagiegurari/rust_info",
        "description": "Extracts the current rust compiler information.",
        "fork": false,
        "stargazers_count": 1,
        "language": "Rust",
        "forks_count": 0
    },
    {
        "name": "sagiegurari.github.io",
        "html_url": "https://github.com/sagiegurari/sagiegurari.github.io",
        "description": "https://sagiegurari.github.io",
        "fork": false,
        "stargazers_count": 1,
        "language": "JavaScript",
        "forks_count": 0
    },
    {
        "name": "scriptexec",
        "html_url": "https://github.com/sagiegurari/scriptexec",
        "description": "Run complex native scripts with a single command, similar to system commands.",
        "fork": false,
        "stargazers_count": 3,
        "language": "R",
        "forks_count": 0
    },
    {
        "name": "shell2batch",
        "html_url": "https://github.com/sagiegurari/shell2batch",
        "description": "Coverts simple basic shell scripts to windows batch scripts.",
        "fork": false,
        "stargazers_count": 2,
        "language": "Rust",
        "forks_count": 0
    },
    {
        "name": "simple-oracledb",
        "html_url": "https://github.com/sagiegurari/simple-oracledb",
        "description": "Extend capabilities of oracledb with simplified API for quicker development.",
        "fork": false,
        "stargazers_count": 21,
        "language": "JavaScript",
        "forks_count": 3
    },
    {
        "name": "simple-web-notification",
        "html_url": "https://github.com/sagiegurari/simple-web-notification",
        "description": "Web Notifications made easy",
        "fork": false,
        "stargazers_count": 12,
        "language": "JavaScript",
        "forks_count": 3
    },
    {
        "name": "simple_redis",
        "html_url": "https://github.com/sagiegurari/simple_redis",
        "description": "Simple and resilient redis client for rust.",
        "fork": false,
        "stargazers_count": 6,
        "language": "Rust",
        "forks_count": 1
    },
    {
        "name": "userscripts-ads-dom-remover",
        "html_url": "https://github.com/sagiegurari/userscripts-ads-dom-remover",
        "description": "Removes Ad Containers from DOM (doesn't replace adblocker extension, but blocks dynamic content which the adblocker fails to block by removing whole sections from the HTML DOM.)",
        "fork": false,
        "stargazers_count": 3,
        "language": "JavaScript",
        "forks_count": 0
    },
    {
        "name": "x2fax",
        "owner": {
            "avatar_url": "https://avatars0.githubusercontent.com/u/8112599?v=4",
            "html_url": "https://github.com/sagiegurari"
        },
        "html_url": "https://github.com/sagiegurari/x2fax",
        "description": "The x2fax (fax4j sub project) is a set of standalone servers and deployable components which enable to provide x2fax capabilities.",
        "fork": false,
        "stargazers_count": 1,
        "language": "Java",
        "forks_count": 0
    }
]
